[{"all_activities":[{"name":"Swimming","description":"Campers will go swimming in Lake Butterfly","location":"Lake Butterfly"},{"name":"Archery","description":"Campers will practice archery at the Butterfly Range","location":"Butterfly Range"}],"calendar_hash":[{"week":{"end_date":"06\/05\/2023","groups":[{"group_campers":[{"id":"1035e216-e038-4541-abe9-a4e5441eb592"},{"id":"45bd6f4e-a88e-448a-b911-1048c5b3ea6a"}],"counselorUUID":"aa8ed9ea-d2c1-413e-b4be-c609ba472aec","group_UUID":"b6a12faa-3eaa-44f5-8a24-62d6e839d41d","group_schedule":[{"daily_activities":[{"name":"Kayaking","description":"Campers will go kayaking in Lake Butterfly","location":"Lake Butterfly"}],"day_of_week":"SUNDAY"},{"daily_activities":[{"name":"Archery","description":"Campers will practice archery at the Butterfly Range","location":"Butterfly Range"}],"day_of_week":"MONDAY"}]}],"theme":"Swimming","isFull":"false","week_counselors":[{"id":"aa8ed9ea-d2c1-413e-b4be-c609ba472aec"}],"week_campers":[{"id":"1035e216-e038-4541-abe9-a4e5441eb592"},{"id":"45bd6f4e-a88e-448a-b911-1048c5b3ea6a"}],"start_date":"05\/29\/2022"},"week_number":1},{"week":{"end_date":"06\/12\/2023","groups":[{"group_campers":[{"id":"1035e216-e038-4541-abe9-a4e5441eb592"},{"id":"45bd6f4e-a88e-448a-b911-1048c5b3ea6a"}],"counselorUUID":"aa8ed9ea-d2c1-413e-b4be-c609ba472aec","group_UUID":"289ff272-2beb-4162-9c15-aeac888d198e","group_schedule":[{"daily_activities":[{"name":"Kayaking","description":"Campers will go kayaking in Lake Butterfly","location":"Lake Butterfly"}],"day_of_week":"SUNDAY"},{"daily_activities":[{"name":"Archery","description":"Campers will practice archery at the Butterfly Range","location":"Butterfly Range"}],"day_of_week":"MONDAY"}]}],"theme":"Nature","isFull":"false","week_counselors":[{"id":"aa8ed9ea-d2c1-413e-b4be-c609ba472aec"}],"week_campers":[{"id":"1035e216-e038-4541-abe9-a4e5441eb592"},{"id":"45bd6f4e-a88e-448a-b911-1048c5b3ea6a"}],"start_date":"06\/06\/2023"},"week_number":2}],"year":2022,"name":"2023 Summer Camp","description":"Fun outdoor camp"},{"all_activities":[{"name":"Kayaking","description":"Campers go kayaking","location":"Lake Smile"},{"name":"Swimming","description":"Campers go swimming","location":"Butterfly Pool"},{"name":"ziplining","description":"Campers go ziplining","location":"Blue Hill"},{"name":"Arts and Crafts","description":"Campers will engage in a variety of Arts and Crafts Projects","location":"AA Room"},{"name":"Soccer","description":"Campers will play soccer","location":"Soccer Field"},{"name":"Archery","description":"Campers will practice archery","location":"Soccer Field"}],"calendar_hash":[{"week":{"end_date":"07\/04\/2023","groups":[],"theme":"hawaiian","isFull":"false","week_counselors":[],"week_campers":[],"start_date":"07\/03\/2023"},"week_number":1},{"week":{"end_date":"07\/14\/2023","groups":[],"theme":"Rockstars","isFull":"false","week_counselors":[],"week_campers":[],"start_date":"07\/10\/2023"},"week_number":2},{"week":{"end_date":"07\/21\/2023","groups":[],"theme":"Ninja Warriors","isFull":"false","week_counselors":[],"week_campers":[],"start_date":"07\/17\/2023"},"week_number":3},{"week":{"end_date":"07\/28\/2023","groups":[],"theme":"Willy Wonka","isFull":"false","week_counselors":[],"week_campers":[],"start_date":"07\/24\/2023"},"week_number":4},{"week":{"end_date":"08\/04\/2023","groups":[],"theme":"Hollywood","isFull":"false","week_counselors":[],"week_campers":[],"start_date":"07\/31\/2023"},"week_number":5},{"week":{"end_date":"08\/11\/2023","groups":[],"theme":"Legos","isFull":"false","week_counselors":[],"week_campers":[],"start_date":"08\/07\/2023"},"week_number":6},{"week":{"end_date":"08\/18\/2023","groups":[],"theme":"Cops and Robbers","isFull":"false","week_counselors":[],"week_campers":[],"start_date":"08\/14\/2023"},"week_number":7},{"week":{"end_date":"08\/25\/2023","groups":[],"theme":"Shark Tank","isFull":"false","week_counselors":[],"week_campers":[],"start_date":"08\/21\/2023"},"week_number":8},{"week":{"end_date":"09\/01\/2023","groups":[],"theme":"Smores","isFull":"false","week_counselors":[],"week_campers":[],"start_date":"08\/28\/2023"},"week_number":9}],"year":2023,"name":"2023 Summer Camp","description":"Super fun Summer Camp"},{"all_activities":[{"name":"Kayaking","description":"go kayaking","location":"Lake smile"},{"name":"swimming","description":"swimming","location":"pool"},{"name":"ziplining","description":"go zip","location":"hill"},{"name":"Arts and Crafts","description":"arts and crafts","location":"AA room"},{"name":"Soccer","description":"play soccer","location":"soccer field"},{"name":"archery","description":"archery","location":"soccer field"}],"calendar_hash":[{"week":{"end_date":"07\/04\/2023","groups":[],"theme":"Hawaiian","isFull":"false","week_counselors":[],"week_campers":[],"start_date":"07\/03\/2023"},"week_number":1},{"week":{"end_date":"07\/14\/2023","groups":[],"theme":"Rockstars","isFull":"false","week_counselors":[],"week_campers":[],"start_date":"07\/10\/2023"},"week_number":2},{"week":{"end_date":"07\/21\/2023","groups":[],"theme":"Ninja Warriors","isFull":"false","week_counselors":[],"week_campers":[],"start_date":"07\/17\/2023"},"week_number":3},{"week":{"end_date":"07\/28\/2023","groups":[],"theme":"Willy Wonka","isFull":"false","week_counselors":[],"week_campers":[],"start_date":"07\/24\/2023"},"week_number":4},{"week":{"end_date":"08\/04\/2023","groups":[],"theme":"Hollywood","isFull":"false","week_counselors":[],"week_campers":[],"start_date":"07\/31\/2023"},"week_number":5},{"week":{"end_date":"08\/11\/2023","groups":[],"theme":"Legos","isFull":"false","week_counselors":[],"week_campers":[],"start_date":"08\/07\/2023"},"week_number":6},{"week":{"end_date":"08\/18\/2023","groups":[],"theme":"Cops and Robbers","isFull":"false","week_counselors":[],"week_campers":[],"start_date":"08\/14\/2023"},"week_number":7},{"week":{"end_date":"08\/25\/2023","groups":[],"theme":"08\/28\/2023","isFull":"false","week_counselors":[],"week_campers":[],"start_date":"08\/21\/2023"},"week_number":8},{"week":{"end_date":"09\/01\/2023","groups":[],"theme":"Smores","isFull":"false","week_counselors":[],"week_campers":[],"start_date":"08\/28\/2023"},"week_number":9}],"year":2023,"name":"2023 Summer Camp","description":"A fun camp where campers can have fun together in a safe and responsible way!"},{"all_activities":[{"name":"Kayaking","description":"kayaking","location":"lake"},{"name":"swimming","description":"swimming","location":"pool"},{"name":"ziplining","description":"ziplining","location":"hill"},{"name":"arts and crafts","description":"arts and crafts","location":"AA room"},{"name":"soccer","description":"soccer","location":"soccer field"},{"name":"archery","description":"archery","location":"soccer field"}],"calendar_hash":[{"week":{"end_date":"07\/04\/2024","groups":[],"theme":"Hawaiian","isFull":"false","week_counselors":[],"week_campers":[],"start_date":"07\/03\/2024"},"week_number":1},{"week":{"end_date":"07\/14\/2024","groups":[],"theme":"Rockstars","isFull":"false","week_counselors":[],"week_campers":[],"start_date":"07\/10\/2024"},"week_number":2},{"week":{"end_date":"07\/17\/2024","groups":[],"theme":"Ninja Warriors","isFull":"false","week_counselors":[],"week_campers":[],"start_date":"07\/12\/2024"},"week_number":3}],"year":2024,"name":"2024 Summer Camp","description":"A fun summer camp"}]